autocurry/__init__.py
tests/__init__.py
tests/test_autocurry.py
Autocurry-0.2.0.dist-info/LICENSE
Autocurry-0.2.0.dist-info/METADATA
Autocurry-0.2.0.dist-info/WHEEL
Autocurry-0.2.0.dist-info/top_level.txt
Autocurry-0.2.0.dist-info/RECORD
