Metadata-Version: 2.1
Name: Autocurry
Version: 0.2.0
Summary: Automatic currying using a decorator
Home-page: https://github.com/felixbr/autocurry
Author: Felix Bruckmeier
Author-email: felix.m.bruckmeier@gmail.com
License: BSD
Download-URL: https://github.com/felixbr/autocurry/tarball/0.2.0
Keywords: functional,currying
Platform: UNKNOWN
